pyCCDA/__init__.py
pyCCDA/core/__init__.py
pyCCDA/core/_core.py
pyCCDA/core/codes.py
pyCCDA/core/wrappers.py
pyCCDA/core/xml.py
pyCCDA/documents/__init__.py
pyCCDA/documents/ccda.py
pyCCDA/parsers/__init__.py
pyCCDA/parsers/ccda.py
pyCCDA/parsers/_ccda/__init__.py
pyCCDA/parsers/_ccda/allergies.py
pyCCDA/parsers/_ccda/care_plan.py
pyCCDA/parsers/_ccda/demographics.py
pyCCDA/parsers/_ccda/document.py
pyCCDA/parsers/_ccda/encounters.py
pyCCDA/parsers/_ccda/free_text.py
pyCCDA/parsers/_ccda/functional_statuses.py
pyCCDA/parsers/_ccda/immunizations.py
pyCCDA/parsers/_ccda/instructions.py
pyCCDA/parsers/_ccda/medications.py
pyCCDA/parsers/_ccda/problems.py
pyCCDA/parsers/_ccda/procedures.py
pyCCDA/parsers/_ccda/results.py
pyCCDA/parsers/_ccda/smoking_status.py
pyCCDA/parsers/_ccda/vitals.py
pyccda-2.0.0.dist-info/licenses/LICENSE
pyccda-2.0.0.dist-info/METADATA
pyccda-2.0.0.dist-info/WHEEL
pyccda-2.0.0.dist-info/top_level.txt
pyccda-2.0.0.dist-info/RECORD
